LICENSE
README.md
setup.py
clrprint/__init__.py
clrprint/__version__.py
clrprint/clrprint.py
clrprint/inputTimeLimit.py
clrprint.egg-info/PKG-INFO
clrprint.egg-info/SOURCES.txt
clrprint.egg-info/dependency_links.txt
clrprint.egg-info/requires.txt
clrprint.egg-info/top_level.txt