Metadata-Version: 2.1
Name: clrprint
Version: 2.0.1
Summary: Print colorfull output in IDLE, powershell, and terminal. Supports on DEBUG feature and      returns None if user input is not entered in given time. 
Home-page: https://github.com/AbhijithAJ/clrprint
Author: ABHIJITH BOPPE
Author-email: abhijithas.eh@gmail.com
License: MIT
Download-URL: https://github.com/AbhijithAJ/clrprint/archive/refs/tags/v2.0.1.tar.gz
Keywords: basic colors,color print,cmd,color idle,color terminal,color powershell,color idle and terminal,color idle, cmd, powershell,input timeout,non blocking input,X-platform,DEBUG,timed input,Cross-platform
Platform: UNKNOWN
Classifier: Development Status :: 5 - Production/Stable
Classifier: License :: OSI Approved :: MIT License
Classifier: Programming Language :: Python
Classifier: Programming Language :: Python :: 3.6
Classifier: Programming Language :: Python :: 3.8
Classifier: Topic :: Software Development :: Build Tools
Classifier: Intended Audience :: Developers
Classifier: Operating System :: OS Independent
Requires-Python: >=3.2
